README.rst
setup.cfg
setup.py
awssig/__init__.py
awssig/dateutil.py
awssig/exc.py
awssig/sigv4.py
awssig.egg-info/PKG-INFO
awssig.egg-info/SOURCES.txt
awssig.egg-info/dependency_links.txt
awssig.egg-info/not-zip-safe
awssig.egg-info/requires.txt
awssig.egg-info/top_level.txt