Metadata-Version: 2.1
Name: awssig
Version: 0.4.0
Summary: AWS signature verification routines
Home-page: https://github.com/dacut/python-aws-sig
Author: David Cuthbert
Author-email: dacut@kanga.org
License: Apache 2.0
Keywords: aws,signature,aws-sigv4
Platform: UNKNOWN
Classifier: Development Status :: 2 - Pre-Alpha
Classifier: Intended Audience :: Developers
Classifier: License :: OSI Approved :: Apache Software License
Classifier: Programming Language :: Python
Classifier: Programming Language :: Python :: 2
Classifier: Programming Language :: Python :: 3
Classifier: Topic :: Software Development :: Libraries :: Python Modules
